Automatic-Version
COPYING
LICENSE
MANIFEST.in
README.md
pyproject.toml
setup.cfg
setup.py
tmsgpack/__init__.py
tmsgpack/api.py
tmsgpack.egg-info/PKG-INFO
tmsgpack.egg-info/SOURCES.txt
tmsgpack.egg-info/dependency_links.txt
tmsgpack.egg-info/top_level.txt